orm_study/__init__.py
orm_study/main.py
orm_study/quiz/__init__.py
orm_study/quiz/_python/변수/multiple_choice.txt
orm_study/quiz/_python/변수/subjective.txt
orm_study/quiz/_python/연산자/multiple_choice.txt
orm_study/quiz/_python/자료형/multiple_choice.txt
orm_study/quiz/_python/조건문/multiple_choice.txt
orm_study/quiz/_resources/PretendardVariable.ttf
orm_study/quiz/_resources/certification.png
orm_study/quiz/certification.py
orm_study/quiz/command.py
orm_study/quiz/constants.py
orm_study/quiz/decorator.py
orm_study/quiz/python.py
orm_study/quiz/reader.py
orm_study-0.1.1.dist-info/LICENSE
orm_study-0.1.1.dist-info/METADATA
orm_study-0.1.1.dist-info/WHEEL
orm_study-0.1.1.dist-info/entry_points.txt
orm_study-0.1.1.dist-info/RECORD
